unlock_joblib_tasks.py
unlock_joblib_tasks-1.3.dist-info/LICENSE
unlock_joblib_tasks-1.3.dist-info/METADATA
unlock_joblib_tasks-1.3.dist-info/WHEEL
unlock_joblib_tasks-1.3.dist-info/top_level.txt
unlock_joblib_tasks-1.3.dist-info/RECORD
