Metadata-Version: 2.1
Name: unlock-joblib-tasks
Version: 1.3
Summary: Unlock the limit of 63 tasks in Windows for the Python joblib library.
Home-page: https://github.com/cnzjy/unlock_joblib_tasks
Author: PlumeSoft
Author-email: master@plumesoft.com
License: BSD 3-Clause
Platform: UNKNOWN
Classifier: Development Status :: 4 - Beta
Classifier: Topic :: System :: Operating System
Classifier: Programming Language :: Python
Classifier: Programming Language :: Python :: 3
Classifier: Programming Language :: Python :: 3.5
Classifier: Programming Language :: Python :: 3.6
Classifier: Programming Language :: Python :: 3.7
Classifier: Programming Language :: Python :: 3.8
Classifier: Programming Language :: Python :: 3.9
Classifier: Programming Language :: Python :: 3.10
Classifier: Programming Language :: Python :: 3.11
Classifier: Programming Language :: Python :: 3.12
License-File: LICENSE
